setup.py
Discipline.egg-info/PKG-INFO
Discipline.egg-info/SOURCES.txt
Discipline.egg-info/dependency_links.txt
Discipline.egg-info/top_level.txt
discipline/__init__.py
discipline/admin.py
discipline/models.py
discipline/management/__init__.py
discipline/management/commands/__init__.py
discipline/management/commands/discipline_migrate.py