Metadata-Version: 1.0
Name: Discipline
Version: 0.9.1
Summary: Discipline: model version control for Django
Home-page: http://github.com/alexeiboronine/discipline
Author: Alexei Boronine
Author-email: alexei.boronine@gmail.com
License: MIT
Download-URL: http://github.com/alexeiboronine/discipline/downloads
Keywords: django versioning version control
Platform: UNKNOWN
Classifier: Development Status :: 4 - Beta
Classifier: Framework :: Django
Classifier: Intended Audience :: Developers
Classifier: Intended Audience :: System Administrators
Classifier: Intended Audience :: System Administrators
Classifier: License :: OSI Approved :: MIT License
Classifier: Operating System :: OS Independent
Classifier: Topic :: Software Development
